{  
   "status":"success",
   "pokemon":[  
      {  
         "id":"77528950",
         "data":"[]",
         "expiration_time":1469238283,
         "pokemonId":"19",
         "latitude":42.276610135556,
         "longitude":-83.732323840051,
         "uid":"883cae449c7:19",
         "is_alive":true
      },
      {  
         "id":"77533938",
         "data":"[]",
         "expiration_time":1469238148,
         "pokemonId":"21",
         "latitude":42.275772991475,
         "longitude":-83.740872616396,
         "uid":"883cae46d8d:46",
         "is_alive":true
      },
      {  
         "id":"77533960",
         "data":"[]",
         "expiration_time":1469238459,
         "pokemonId":"46",
         "latitude":42.276327482145,
         "longitude":-83.738382802994,
         "uid":"883cae46d8d:46",
         "is_alive":true
      },
      {  
         "id":"77543642",
         "data":"[]",
         "expiration_time":1469238499,
         "pokemonId":"16",
         "latitude":42.277952404589,
         "longitude":-83.740042689689,
         "uid":"883cae40b9d:16",
         "is_alive":true
      },
      {  
         "id":"77543692",
         "data":"[]",
         "expiration_time":1469238474,
         "pokemonId":"21",
         "latitude":42.276851222509,
         "longitude":-83.739544728339,
         "uid":"883cae40b9d:16",
         "is_alive":true
      },
      {  
         "id":"77543746",
         "data":"[]",
         "expiration_time":1469238683,
         "pokemonId":"16",
         "latitude":42.278710780376,
         "longitude":-83.741287575589,
         "uid":"883cae40b9d:16",
         "is_alive":true
      },
      {  
         "id":"77543787",
         "data":"[]",
         "expiration_time":1469238483,
         "pokemonId":"21",
         "latitude":42.27852141471,
         "longitude":-83.742034495148,
         "uid":"883cae40b9d:16",
         "is_alive":true
      },
      {  
         "id":"77543830",
         "data":"[]",
         "expiration_time":1469238347,
         "pokemonId":"13",
         "latitude":42.278444398601,
         "longitude":-83.740623639549,
         "uid":"883cae40b9d:16",
         "is_alive":true
      },
      {  
         "id":"77557341",
         "data":"[]",
         "expiration_time":1469238105,
         "pokemonId":"16",
         "latitude":42.282591832966,
         "longitude":-83.743528307306,
         "uid":"883cae157e9:16",
         "is_alive":true
      },
      {  
         "id":"77567940",
         "data":"[]",
         "expiration_time":1469238053,
         "pokemonId":"21",
         "latitude":42.275112530207,
         "longitude":-83.734398893904,
         "uid":"883cae45b47:13",
         "is_alive":true
      },
      {  
         "id":"77567993",
         "data":"[]",
         "expiration_time":1469238688,
         "pokemonId":"13",
         "latitude":42.274336287059,
         "longitude":-83.734232892147,
         "uid":"883cae45b47:13",
         "is_alive":true
      },
      {  
         "id":"77568038",
         "data":"[]",
         "expiration_time":1469238544,
         "pokemonId":"21",
         "latitude":42.274669974073,
         "longitude":-83.733319874551,
         "uid":"883cae45b47:13",
         "is_alive":true
      },
      {  
         "id":"77568077",
         "data":"[]",
         "expiration_time":1469238161,
         "pokemonId":"19",
         "latitude":42.27560004172,
         "longitude":-83.734896896515,
         "uid":"883cae45b47:13",
         "is_alive":true
      },
      {  
         "id":"77568115",
         "data":"[]",
         "expiration_time":1469238364,
         "pokemonId":"19",
         "latitude":42.275270881646,
         "longitude":-83.735892889759,
         "uid":"883cae45b47:13",
         "is_alive":true
      },
      {  
         "id":"77568153",
         "data":"[]",
         "expiration_time":1469238652,
         "pokemonId":"16",
         "latitude":42.274656363581,
         "longitude":-83.733070867423,
         "uid":"883cae45b47:13",
         "is_alive":true
      },
      {  
         "id":"77571672",
         "data":"[]",
         "expiration_time":1469238238,
         "pokemonId":"19",
         "latitude":42.277283973094,
         "longitude":-83.737635839506,
         "uid":"883cae415f7:16",
         "is_alive":true
      },
      {  
         "id":"77571713",
         "data":"[]",
         "expiration_time":1469238683,
         "pokemonId":"13",
         "latitude":42.276738251664,
         "longitude":-83.738880773661,
         "uid":"883cae415f7:16",
         "is_alive":true
      },
      {  
         "id":"77571746",
         "data":"[]",
         "expiration_time":1469238201,
         "pokemonId":"16",
         "latitude":42.27624134899,
         "longitude":-83.736805869536,
         "uid":"883cae415f7:16",
         "is_alive":true
      },
      {  
         "id":"77571816",
         "data":"[]",
         "expiration_time":1469238647,
         "pokemonId":"16",
         "latitude":42.27832203937,
         "longitude":-83.738382802994,
         "uid":"883cae415f7:16",
         "is_alive":true
      },
      {  
         "id":"77571836",
         "data":"[]",
         "expiration_time":1469238687,
         "pokemonId":"16",
         "latitude":42.278109315453,
         "longitude":-83.735892889759,
         "uid":"883cae415f7:16",
         "is_alive":true
      },
      {  
         "id":"77602635",
         "data":"[]",
         "expiration_time":1469238744,
         "pokemonId":"21",
         "latitude":42.276504206512,
         "longitude":-83.741619540947,
         "uid":"883cae40999:96",
         "is_alive":true
      },
      {  
         "id":"77602688",
         "data":"[]",
         "expiration_time":1469238760,
         "pokemonId":"96",
         "latitude":42.278827958839,
         "longitude":-83.740623639549,
         "uid":"883cae40999:96",
         "is_alive":true
      },
      {  
         "id":"77609770",
         "data":"[]",
         "expiration_time":1469238168,
         "pokemonId":"43",
         "latitude":42.279577547698,
         "longitude":-83.74311336309,
         "uid":"883cae3f0f5:43",
         "is_alive":true
      },
      {  
         "id":"77610430",
         "data":"[]",
         "expiration_time":1469238150,
         "pokemonId":"52",
         "latitude":42.274997594171,
         "longitude":-83.744939096891,
         "uid":"883cae39a0f:52",
         "is_alive":true
      },
      {  
         "id":"77611993",
         "data":"[]",
         "expiration_time":1469238261,
         "pokemonId":"96",
         "latitude":42.279140189052,
         "longitude":-83.744939096891,
         "uid":"883cae3f0f5:43",
         "is_alive":true
      },
      {  
         "id":"77612052",
         "data":"[]",
         "expiration_time":1469238541,
         "pokemonId":"19",
         "latitude":42.278837868722,
         "longitude":-83.745022083515,
         "uid":"883cae3f0f5:43",
         "is_alive":true
      },
      {  
         "id":"77612127",
         "data":"[]",
         "expiration_time":1469238650,
         "pokemonId":"124",
         "latitude":42.27970885909,
         "longitude":-83.745520000928,
         "uid":"883cae3f0f5:43",
         "is_alive":true
      },
      {  
         "id":"77613955",
         "data":"[]",
         "expiration_time":1469238763,
         "pokemonId":"93",
         "latitude":42.280137679319,
         "longitude":-83.746349854407,
         "uid":"883cae3e8eb:124",
         "is_alive":true
      },
      {  
         "id":"77614000",
         "data":"[]",
         "expiration_time":1469238333,
         "pokemonId":"16",
         "latitude":42.278657529073,
         "longitude":-83.745934929055,
         "uid":"883cae3e8eb:124",
         "is_alive":true
      },
      {  
         "id":"77614057",
         "data":"[]",
         "expiration_time":1469238647,
         "pokemonId":"16",
         "latitude":42.278653002374,
         "longitude":-83.745851943652,
         "uid":"883cae3e8eb:124",
         "is_alive":true
      },
      {  
         "id":"77614151",
         "data":"[]",
         "expiration_time":1469238613,
         "pokemonId":"16",
         "latitude":42.278955324754,
         "longitude":-83.745768958137,
         "uid":"883cae3e8eb:124",
         "is_alive":true
      },
      {  
         "id":"77614360",
         "data":"[]",
         "expiration_time":1469238173,
         "pokemonId":"96",
         "latitude":42.280191990786,
         "longitude":-83.747345663934,
         "uid":"883cae3e8eb:124",
         "is_alive":true
      },
      {  
         "id":"77616299",
         "data":"[]",
         "expiration_time":1469238391,
         "pokemonId":"96",
         "latitude":42.277696688473,
         "longitude":-83.748009528074,
         "uid":"883cae3ea33:16",
         "is_alive":true
      },
      {  
         "id":"77616539",
         "data":"[]",
         "expiration_time":1469238413,
         "pokemonId":"41",
         "latitude":42.276979106056,
         "longitude":-83.747511630635,
         "uid":"883cae3ea33:16",
         "is_alive":true
      },
      {  
         "id":"77634651",
         "data":"[]",
         "expiration_time":1469238666,
         "pokemonId":"19",
         "latitude":42.278244600561,
         "longitude":-83.735560893786,
         "uid":"883cae43e0b:19",
         "is_alive":true
      },
      {  
         "id":"77648204",
         "data":"[]",
         "expiration_time":1469238799,
         "pokemonId":"124",
         "latitude":42.279613777119,
         "longitude":-83.743777272504,
         "uid":"883cae3f425:21",
         "is_alive":true
      },
      {  
         "id":"77659914",
         "data":"[]",
         "expiration_time":1469238421,
         "pokemonId":"96",
         "latitude":42.279831272267,
         "longitude":-83.749171273227,
         "uid":"883cae3d9c7:96",
         "is_alive":true
      },
      {  
         "id":"77659954",
         "data":"[]",
         "expiration_time":1469238207,
         "pokemonId":"96",
         "latitude":42.279276387202,
         "longitude":-83.750250017106,
         "uid":"883cae3d9c7:96",
         "is_alive":true
      },
      {  
         "id":"77660002",
         "data":"[]",
         "expiration_time":1469238546,
         "pokemonId":"16",
         "latitude":42.280169582186,
         "longitude":-83.74834145748,
         "uid":"883cae3d9c7:96",
         "is_alive":true
      },
      {  
         "id":"77660047",
         "data":"[]",
         "expiration_time":1469238119,
         "pokemonId":"41",
         "latitude":42.280395188522,
         "longitude":-83.748258475295,
         "uid":"883cae3d9c7:96",
         "is_alive":true
      },
      {  
         "id":"77660093",
         "data":"[]",
         "expiration_time":1469238508,
         "pokemonId":"96",
         "latitude":42.281884334735,
         "longitude":-83.74883934826,
         "uid":"883cae3d9c7:96",
         "is_alive":true
      },
      {  
         "id":"77676985",
         "data":"[]",
         "expiration_time":1469238831,
         "pokemonId":"16",
         "latitude":42.278164416961,
         "longitude":-83.739710715899,
         "uid":"883cae40c73:16",
         "is_alive":true
      },
      {  
         "id":"77688383",
         "data":"[]",
         "expiration_time":1469238230,
         "pokemonId":"97",
         "latitude":42.283235931321,
         "longitude":-83.738465798383,
         "uid":"883cae6a603:97",
         "is_alive":true
      },
      {  
         "id":"77690687",
         "data":"[]",
         "expiration_time":1469238815,
         "pokemonId":"21",
         "latitude":42.277261654172,
         "longitude":-83.738631788827,
         "uid":"883cae41205:16",
         "is_alive":true
      },
      {  
         "id":"77690726",
         "data":"[]",
         "expiration_time":1469238410,
         "pokemonId":"96",
         "latitude":42.278845762815,
         "longitude":-83.739544728339,
         "uid":"883cae41205:16",
         "is_alive":true
      },
      {  
         "id":"77696482",
         "data":"[]",
         "expiration_time":1469238110,
         "pokemonId":"16",
         "latitude":42.280646021132,
         "longitude":-83.738797778828,
         "uid":"883cae41b9b:19",
         "is_alive":true
      },
      {  
         "id":"77696547",
         "data":"[]",
         "expiration_time":1469238623,
         "pokemonId":"16",
         "latitude":42.28070877701,
         "longitude":-83.737137858855,
         "uid":"883cae41b9b:19",
         "is_alive":true
      },
      {  
         "id":"77696654",
         "data":"[]",
         "expiration_time":1469238627,
         "pokemonId":"19",
         "latitude":42.280663802895,
         "longitude":-83.737718835892,
         "uid":"883cae41b9b:19",
         "is_alive":true
      },
      {  
         "id":"77696716",
         "data":"[]",
         "expiration_time":1469238613,
         "pokemonId":"16",
         "latitude":42.28026212364,
         "longitude":-83.737386849679,
         "uid":"883cae41b9b:19",
         "is_alive":true
      },
      {  
         "id":"77696778",
         "data":"[]",
         "expiration_time":1469238665,
         "pokemonId":"16",
         "latitude":42.280303263981,
         "longitude":-83.739544728339,
         "uid":"883cae41b9b:19",
         "is_alive":true
      },
      {  
         "id":"77697136",
         "data":"[]",
         "expiration_time":1469238144,
         "pokemonId":"96",
         "latitude":42.279822013658,
         "longitude":-83.747594613819,
         "uid":"883cae3dccd:96",
         "is_alive":true
      },
      {  
         "id":"77697403",
         "data":"[]",
         "expiration_time":1469238830,
         "pokemonId":"16",
         "latitude":42.276123825481,
         "longitude":-83.736058887081,
         "uid":"883cae46a13:16",
         "is_alive":true
      },
      {  
         "id":"77697439",
         "data":"[]",
         "expiration_time":1469238850,
         "pokemonId":"19",
         "latitude":42.277076497086,
         "longitude":-83.738050820331,
         "uid":"883cae46a13:16",
         "is_alive":true
      },
      {  
         "id":"77706613",
         "data":"[]",
         "expiration_time":1469238547,
         "pokemonId":"19",
         "latitude":42.28168620474,
         "longitude":-83.73116177962,
         "uid":"883cae680e5:21",
         "is_alive":true
      },
      {  
         "id":"77706658",
         "data":"[]",
         "expiration_time":1469238811,
         "pokemonId":"13",
         "latitude":42.280332695378,
         "longitude":-83.73165980818,
         "uid":"883cae680e5:21",
         "is_alive":true
      },
      {  
         "id":"77706703",
         "data":"[]",
         "expiration_time":1469238871,
         "pokemonId":"19",
         "latitude":42.28014794674,
         "longitude":-83.73248984691,
         "uid":"883cae680e5:21",
         "is_alive":true
      },
      {  
         "id":"77706752",
         "data":"[]",
         "expiration_time":1469238344,
         "pokemonId":"16",
         "latitude":42.281966244754,
         "longitude":-83.732074828931,
         "uid":"883cae680e5:21",
         "is_alive":true
      },
      {  
         "id":"77706846",
         "data":"[]",
         "expiration_time":1469238418,
         "pokemonId":"21",
         "latitude":42.282525433617,
         "longitude":-83.731078774472,
         "uid":"883cae680e5:21",
         "is_alive":true
      },
      {  
         "id":"77750242",
         "data":"[]",
         "expiration_time":1469238191,
         "pokemonId":"13",
         "latitude":42.277752579215,
         "longitude":-83.734979896562,
         "uid":"883cae43cd3:133",
         "is_alive":true
      },
      {  
         "id":"77750293",
         "data":"[]",
         "expiration_time":1469238235,
         "pokemonId":"41",
         "latitude":42.279038538409,
         "longitude":-83.734647895709,
         "uid":"883cae43cd3:133",
         "is_alive":true
      },
      {  
         "id":"77750347",
         "data":"[]",
         "expiration_time":1469238119,
         "pokemonId":"19",
         "latitude":42.278546913224,
         "longitude":-83.735477894515,
         "uid":"883cae43cd3:133",
         "is_alive":true
      },
      {  
         "id":"77750414",
         "data":"[]",
         "expiration_time":1469238406,
         "pokemonId":"19",
         "latitude":42.277987252538,
         "longitude":-83.735062896498,
         "uid":"883cae43cd3:133",
         "is_alive":true
      },
      {  
         "id":"77750464",
         "data":"[]",
         "expiration_time":1469238841,
         "pokemonId":"19",
         "latitude":42.278763820705,
         "longitude":-83.736639874211,
         "uid":"883cae43cd3:133",
         "is_alive":true
      },
      {  
         "id":"77750510",
         "data":"[]",
         "expiration_time":1469238854,
         "pokemonId":"133",
         "latitude":42.279444769412,
         "longitude":-83.735062896498,
         "uid":"883cae43cd3:133",
         "is_alive":true
      }
   ]
}